odoo/addons/server_action_mass_edit/README.rst
odoo/addons/server_action_mass_edit/__init__.py
odoo/addons/server_action_mass_edit/__manifest__.py
odoo/addons/server_action_mass_edit/hooks.py
odoo/addons/server_action_mass_edit/demo/mass_editing.xml
odoo/addons/server_action_mass_edit/i18n/am.po
odoo/addons/server_action_mass_edit/i18n/ar.po
odoo/addons/server_action_mass_edit/i18n/bg.po
odoo/addons/server_action_mass_edit/i18n/bs.po
odoo/addons/server_action_mass_edit/i18n/ca.po
odoo/addons/server_action_mass_edit/i18n/cs.po
odoo/addons/server_action_mass_edit/i18n/da.po
odoo/addons/server_action_mass_edit/i18n/de.po
odoo/addons/server_action_mass_edit/i18n/el_GR.po
odoo/addons/server_action_mass_edit/i18n/en_GB.po
odoo/addons/server_action_mass_edit/i18n/es.po
odoo/addons/server_action_mass_edit/i18n/es_AR.po
odoo/addons/server_action_mass_edit/i18n/es_CL.po
odoo/addons/server_action_mass_edit/i18n/es_CO.po
odoo/addons/server_action_mass_edit/i18n/es_CR.po
odoo/addons/server_action_mass_edit/i18n/es_DO.po
odoo/addons/server_action_mass_edit/i18n/es_EC.po
odoo/addons/server_action_mass_edit/i18n/es_ES.po
odoo/addons/server_action_mass_edit/i18n/es_MX.po
odoo/addons/server_action_mass_edit/i18n/es_PE.po
odoo/addons/server_action_mass_edit/i18n/es_PY.po
odoo/addons/server_action_mass_edit/i18n/es_VE.po
odoo/addons/server_action_mass_edit/i18n/et.po
odoo/addons/server_action_mass_edit/i18n/eu.po
odoo/addons/server_action_mass_edit/i18n/fa.po
odoo/addons/server_action_mass_edit/i18n/fi.po
odoo/addons/server_action_mass_edit/i18n/fr.po
odoo/addons/server_action_mass_edit/i18n/fr_CA.po
odoo/addons/server_action_mass_edit/i18n/fr_CH.po
odoo/addons/server_action_mass_edit/i18n/fr_FR.po
odoo/addons/server_action_mass_edit/i18n/gl.po
odoo/addons/server_action_mass_edit/i18n/gl_ES.po
odoo/addons/server_action_mass_edit/i18n/he.po
odoo/addons/server_action_mass_edit/i18n/hr.po
odoo/addons/server_action_mass_edit/i18n/hr_HR.po
odoo/addons/server_action_mass_edit/i18n/hu.po
odoo_addon_server_action_mass_edit-18.0.1.1.1.dist-info/METADATA
odoo_addon_server_action_mass_edit-18.0.1.1.1.dist-info/WHEEL
odoo_addon_server_action_mass_edit-18.0.1.1.1.dist-info/top_level.txt
odoo_addon_server_action_mass_edit-18.0.1.1.1.dist-info/RECORD
