Metadata-Version: 2.1
Name: odoo-addon-server_action_mass_edit
Version: 18.0.1.1.1
Requires-Python: >=3.10
Requires-Dist: odoo==18.0.*
Requires-Dist: openupgradelib
Summary: Mass Editing
Home-page: https://github.com/OCA/server-ux
License: AGPL-3
Author: =?utf-8?q?Serpent_Consulting_Services_Pvt=2E_Ltd=2E=2C_Tecnativa=2C_GRAP=2C_Iv=C3=A1n_Todorovich=2C_Odoo_Community_Association_=28OCA=29?=
Author-email: support@odoo-community.org
Classifier: Programming Language :: Python
Classifier: Framework :: Odoo
Classifier: Framework :: Odoo :: 18.0
Classifier: License :: OSI Approved :: GNU Affero General Public License v3
